{
  "basicInfo": {
    "name": "Christopher Austin",
    "investorTypes": [
      "Investor"
    ]
  },
  "investingProfile": {},
  "sectorRankings": [
    {
      "name": "TransportationTech (Seed)",
      "url": "https://signal.nfx.com/investor-lists/top-transportationtech-seed-investors"
    },
    {
      "name": "Social Networks (Seed)",
      "url": "https://signal.nfx.com/investor-lists/top-social-networks-seed-investors"
    },
    {
      "name": "E-commerce (Seed)",
      "url": "https://signal.nfx.com/investor-lists/top-e-commerce-seed-investors"
    },
    {
      "name": "Consumer Internet (Seed)",
      "url": "https://signal.nfx.com/investor-lists/top-consumer-internet-seed-investors"
    },
    {
      "name": "San Francisco Bay Area",
      "url": "https://signal.nfx.com/investor-lists/top-san-francisco-bay-area-investors"
    },
    {
      "name": "TransportationTech (Pre-seed)",
      "url": "https://signal.nfx.com/investor-lists/top-transportationtech-pre-seed-investors"
    },
    {
      "name": "Social Networks (Pre-seed)",
      "url": "https://signal.nfx.com/investor-lists/top-social-networks-pre-seed-investors"
    },
    {
      "name": "E-commerce (Pre-seed)",
      "url": "https://signal.nfx.com/investor-lists/top-e-commerce-pre-seed-investors"
    },
    {
      "name": "Marketplaces (Pre-seed)",
      "url": "https://signal.nfx.com/investor-lists/top-marketplaces-pre-seed-investors"
    },
    {
      "name": "Consumer Internet (Pre-seed)",
      "url": "https://signal.nfx.com/investor-lists/top-consumer-internet-pre-seed-investors"
    },
    {
      "name": "Enterprise (Pre-seed)",
      "url": "https://signal.nfx.com/investor-lists/top-enterprise-pre-seed-investors"
    },
    {
      "name": "Marketplaces (Seed)",
      "url": "https://signal.nfx.com/investor-lists/top-marketplaces-seed-investors"
    },
    {
      "name": "Enterprise (Seed)",
      "url": "https://signal.nfx.com/investor-lists/top-enterprise-seed-investors"
    }
  ],
  "investments": [],
  "experience": [
    {
      "position": "Partner",
      "company": "Goodwin Procter LLP",
      "dates": "2010 - 2014"
    },
    {
      "position": "Partner",
      "company": "Ropes & Gray LLP",
      "dates": "1994 - 2010"
    },
    {
      "position": "Attorney",
      "company": "Hughes Hubbard & Reed",
      "dates": "1992 - 1994"
    },
    {
      "position": "Analyst",
      "company": "Washington State Senate",
      "dates": "1987 - 1989"
    },
    {
      "position": "Partner",
      "company": "Orrick, Herrington & Sutcliffe LLP",
      "dates": "2014 - Present"
    }
  ],
  "socials": {
    "linkedin": "https://www.linkedin.com/pub/christopher-austin/0/111/381/",
    "angellist": "https://www.angel.co/christopher-austin",
    "crunchbase": "https://www.crunchbase.com/person/christopher-austin"
  },
  "profilePicture": null,
  "profileUrl": "https://signal.nfx.com/investors/christopher-austin",
  "slug": "christopher-austin",
  "scraped_at": "2026-02-24T10:48:28.980476"
}