{
  "basicInfo": {
    "investorTypes": [
      "Investor"
    ],
    "name": "Pandu Ranganath"
  },
  "experience": [
    {
      "company": "Synchronoss",
      "dates": "2010 - 2016",
      "position": "Director of Product Management - Consumer Mobile App, UX, Cloud & Analytics, B2B, B2C"
    },
    {
      "company": "FusionOne (Cloud, SaaS, Mobile, Web)",
      "dates": "2008 - 2010",
      "position": "Director of Product Management"
    },
    {
      "company": "Seven Networks",
      "dates": "2007 - 2008",
      "position": "Director of Engineering, Advanced Products (Messaging)"
    },
    {
      "company": "Bytemobile Inc (Acquired by Citrix in 2012)",
      "dates": "2005 - 2007",
      "position": "Director of engineering"
    },
    {
      "company": "Openwave Systems, Inc",
      "dates": "2000 - 2005",
      "position": "Director of Engineering (last position)"
    },
    {
      "company": "Vanguard Information Systems",
      "dates": "1997 - 1999",
      "position": "Founder"
    },
    {
      "company": "Xfinity Home",
      "dates": "2016 - Present",
      "position": "Product Management - Bigdata, AWS, IoT, ML (Consulting)"
    },
    {
      "company": "Datadistil.net (Machine Learning)",
      "dates": "2016 - Present",
      "position": "Co-Founder/CTO"
    }
  ],
  "investingProfile": {},
  "investments": [],
  "profilePicture": null,
  "profileUrl": "https://signal.nfx.com/investors/pandu-ranganath",
  "sectorRankings": [
    {
      "name": "Local Services (Seed)",
      "url": "https://signal.nfx.com/investor-lists/top-local-services-seed-investors"
    },
    {
      "name": "Media/Content (Seed)",
      "url": "https://signal.nfx.com/investor-lists/top-media-content-seed-investors"
    },
    {
      "name": "Social Networks (Seed)",
      "url": "https://signal.nfx.com/investor-lists/top-social-networks-seed-investors"
    },
    {
      "name": "IoT (Seed)",
      "url": "https://signal.nfx.com/investor-lists/top-iot-seed-investors"
    },
    {
      "name": "Consumer Health (Seed)",
      "url": "https://signal.nfx.com/investor-lists/top-consumer-health-seed-investors"
    },
    {
      "name": "AI (Seed)",
      "url": "https://signal.nfx.com/investor-lists/top-ai-seed-investors"
    },
    {
      "name": "San Francisco Bay Area",
      "url": "https://signal.nfx.com/investor-lists/top-san-francisco-bay-area-investors"
    },
    {
      "name": "Local Services (Pre-seed)",
      "url": "https://signal.nfx.com/investor-lists/top-local-services-pre-seed-investors"
    },
    {
      "name": "Media/Content (Pre-seed)",
      "url": "https://signal.nfx.com/investor-lists/top-media-content-pre-seed-investors"
    },
    {
      "name": "IoT (Pre-seed)",
      "url": "https://signal.nfx.com/investor-lists/top-iot-pre-seed-investors"
    },
    {
      "name": "Social Networks (Pre-seed)",
      "url": "https://signal.nfx.com/investor-lists/top-social-networks-pre-seed-investors"
    },
    {
      "name": "Consumer Health (Pre-seed)",
      "url": "https://signal.nfx.com/investor-lists/top-consumer-health-pre-seed-investors"
    },
    {
      "name": "Health & Hospital Services (Pre-seed)",
      "url": "https://signal.nfx.com/investor-lists/top-health-hospital-services-pre-seed-investors"
    },
    {
      "name": "AI (Pre-seed)",
      "url": "https://signal.nfx.com/investor-lists/top-ai-pre-seed-investors"
    },
    {
      "name": "Enterprise (Pre-seed)",
      "url": "https://signal.nfx.com/investor-lists/top-enterprise-pre-seed-investors"
    },
    {
      "name": "FinTech (Pre-seed)",
      "url": "https://signal.nfx.com/investor-lists/top-fintech-pre-seed-investors"
    },
    {
      "name": "Health & Hospital Services (Seed)",
      "url": "https://signal.nfx.com/investor-lists/top-health-hospital-services-seed-investors"
    },
    {
      "name": "FinTech (Seed)",
      "url": "https://signal.nfx.com/investor-lists/top-fintech-seed-investors"
    },
    {
      "name": "Enterprise (Seed)",
      "url": "https://signal.nfx.com/investor-lists/top-enterprise-seed-investors"
    }
  ],
  "slug": "pandu-ranganath",
  "socials": {
    "angellist": "https://www.angel.co/pandu-ranganath",
    "crunchbase": "https://www.crunchbase.com/person/pandu-ranganath",
    "linkedin": "https://www.linkedin.com/in/pandu/"
  },
  "scraped_at": "2026-02-28T02:30:05.612878"
}