{
  "basicInfo": {
    "investorTypes": [
      "VC",
      "Investor"
    ],
    "location": "New York City",
    "name": "Ravi Chari",
    "website": "https://alaya-capital.com/"
  },
  "experience": [],
  "investingProfile": {
    "currentPosition": {
      "firm": "Alaya Capital",
      "firmUrl": "https://signal.nfx.com/firms/alaya-capital-partners",
      "position": "Principal"
    },
    "investmentRange": "$100K - $5.0M",
    "sweetSpot": "$1.5M"
  },
  "investments": [],
  "profilePicture": null,
  "profileUrl": "https://signal.nfx.com/investors/ravi-chari",
  "sectorRankings": [
    {
      "name": "Enterprise (Series A)",
      "url": "https://signal.nfx.com/investor-lists/top-enterprise-series-a-investors"
    },
    {
      "name": "New York City",
      "url": "https://signal.nfx.com/investor-lists/top-new-york-city-investors"
    },
    {
      "name": "Consumer Internet (Seed)",
      "url": "https://signal.nfx.com/investor-lists/top-consumer-internet-seed-investors"
    },
    {
      "name": "Consumer Internet (Series A)",
      "url": "https://signal.nfx.com/investor-lists/top-consumer-internet-series-a-investors"
    },
    {
      "name": "Enterprise (Seed)",
      "url": "https://signal.nfx.com/investor-lists/top-enterprise-seed-investors"
    }
  ],
  "slug": "ravi-chari",
  "socials": {
    "angellist": "https://www.angel.co/u/ravi-chari",
    "linkedin": "https://www.linkedin.com/in/rchari/",
    "website": "https://www.alaya-capital.com/"
  },
  "scraped_at": "2026-02-28T02:43:35.786578"
}