{
  "basicInfo": {
    "investorTypes": [
      "Investor"
    ],
    "name": "Roberto Singler"
  },
  "experience": [
    {
      "company": "TrenDemon",
      "dates": "2015 - 2018",
      "position": "Director"
    },
    {
      "company": "Poliphone",
      "dates": "2014 - 2016",
      "position": "Director"
    },
    {
      "company": "Directa Club",
      "dates": "2008 - 2009",
      "position": "CEO"
    },
    {
      "company": "servicefriend",
      "dates": "2015 - Present",
      "position": "Director"
    },
    {
      "company": "Blue Ocean Hub",
      "dates": "2013 - Present",
      "position": "CEO"
    },
    {
      "company": "Young Engineers e2",
      "dates": "2011 - Present",
      "position": "Director"
    },
    {
      "company": "TuSeguro.com",
      "dates": "2008 - Present",
      "position": "Director"
    },
    {
      "company": "Directa Group",
      "dates": "1998 - Present",
      "position": "President"
    }
  ],
  "investingProfile": {
    "investmentRange": "$100K - $250K"
  },
  "investments": [],
  "profilePicture": null,
  "profileUrl": "https://signal.nfx.com/investors/roberto-singler",
  "sectorRankings": [
    {
      "name": "Advertising (Seed)",
      "url": "https://signal.nfx.com/investor-lists/top-advertising-seed-investors"
    },
    {
      "name": "Media/Content (Seed)",
      "url": "https://signal.nfx.com/investor-lists/top-media-content-seed-investors"
    },
    {
      "name": "Social Networks (Seed)",
      "url": "https://signal.nfx.com/investor-lists/top-social-networks-seed-investors"
    },
    {
      "name": "IoT (Seed)",
      "url": "https://signal.nfx.com/investor-lists/top-iot-seed-investors"
    },
    {
      "name": "Education (Seed)",
      "url": "https://signal.nfx.com/investor-lists/top-education-seed-investors"
    },
    {
      "name": "Israel",
      "url": "https://signal.nfx.com/investor-lists/top-israel-investors"
    },
    {
      "name": "Advertising (Pre-seed)",
      "url": "https://signal.nfx.com/investor-lists/top-advertising-pre-seed-investors"
    },
    {
      "name": "IoT (Pre-seed)",
      "url": "https://signal.nfx.com/investor-lists/top-iot-pre-seed-investors"
    },
    {
      "name": "Education (Pre-seed)",
      "url": "https://signal.nfx.com/investor-lists/top-education-pre-seed-investors"
    },
    {
      "name": "Media/Content (Pre-seed)",
      "url": "https://signal.nfx.com/investor-lists/top-media-content-pre-seed-investors"
    },
    {
      "name": "Social Networks (Pre-seed)",
      "url": "https://signal.nfx.com/investor-lists/top-social-networks-pre-seed-investors"
    },
    {
      "name": "Enterprise (Pre-seed)",
      "url": "https://signal.nfx.com/investor-lists/top-enterprise-pre-seed-investors"
    },
    {
      "name": "SaaS (Pre-seed)",
      "url": "https://signal.nfx.com/investor-lists/top-saas-pre-seed-investors"
    },
    {
      "name": "SaaS (Seed)",
      "url": "https://signal.nfx.com/investor-lists/top-saas-seed-investors"
    },
    {
      "name": "Enterprise (Seed)",
      "url": "https://signal.nfx.com/investor-lists/top-enterprise-seed-investors"
    }
  ],
  "slug": "roberto-singler",
  "socials": {
    "crunchbase": "https://www.crunchbase.com/person/robert-singer",
    "linkedin": "https://www.linkedin.com/in/robertosingler/"
  },
  "scraped_at": "2026-02-27T04:05:58.302571"
}