{
  "basicInfo": {
    "name": "Don Hutchison",
    "investorTypes": [
      "Angel"
    ]
  },
  "investingProfile": {
    "currentPosition": "Angel"
  },
  "sectorRankings": [
    {
      "name": "Sales & CRM (Seed)",
      "url": "https://signal.nfx.com/investor-lists/top-sales-crm-seed-investors"
    },
    {
      "name": "Social Networks (Seed)",
      "url": "https://signal.nfx.com/investor-lists/top-social-networks-seed-investors"
    },
    {
      "name": "Data Services (Seed)",
      "url": "https://signal.nfx.com/investor-lists/top-data-services-seed-investors"
    },
    {
      "name": "San Francisco Bay Area",
      "url": "https://signal.nfx.com/investor-lists/top-san-francisco-bay-area-investors"
    },
    {
      "name": "Data Services (Pre-seed)",
      "url": "https://signal.nfx.com/investor-lists/top-data-services-pre-seed-investors"
    },
    {
      "name": "Sales & CRM (Pre-seed)",
      "url": "https://signal.nfx.com/investor-lists/top-sales-crm-pre-seed-investors"
    },
    {
      "name": "Social Networks (Pre-seed)",
      "url": "https://signal.nfx.com/investor-lists/top-social-networks-pre-seed-investors"
    },
    {
      "name": "Marketplaces (Pre-seed)",
      "url": "https://signal.nfx.com/investor-lists/top-marketplaces-pre-seed-investors"
    },
    {
      "name": "Marketplaces (Seed)",
      "url": "https://signal.nfx.com/investor-lists/top-marketplaces-seed-investors"
    }
  ],
  "investments": [],
  "experience": [
    {
      "position": "Director",
      "company": "Marin Software",
      "dates": "2007 - 2017"
    },
    {
      "position": "Co-founder & Chairman",
      "company": "Recurrent Energy",
      "dates": "2006 - 2008"
    },
    {
      "position": "CEO & COB",
      "company": "Work.com",
      "dates": "2000 - 2001"
    },
    {
      "position": "SVP & GM",
      "company": "Excite@Home",
      "dates": "1997 - 2000"
    },
    {
      "position": "SVP Sales & Marketing",
      "company": "Netcom Communications",
      "dates": "1994 - 1997"
    },
    {
      "position": "Director, Sales, Marketing, Business Development & Client Services",
      "company": "Pixar, Prime Computer, Data General",
      "dates": "1982 - 1994"
    }
  ],
  "socials": {
    "linkedin": "https://www.linkedin.com/in/dphutch/",
    "angellist": "https://www.angel.co/dphutch",
    "crunchbase": "https://www.crunchbase.com/person/don-hutchison"
  },
  "profilePicture": null,
  "profileUrl": "https://signal.nfx.com/investors/don-hutchison",
  "slug": "don-hutchison",
  "scraped_at": "2026-02-24T10:57:26.912909"
}