{
  "basicInfo": {
    "name": "Vince Monical",
    "investorTypes": [
      "Investor"
    ]
  },
  "investingProfile": {},
  "sectorRankings": [
    {
      "name": "AI (Seed)",
      "url": "https://signal.nfx.com/investor-lists/top-ai-seed-investors"
    },
    {
      "name": "E-commerce (Seed)",
      "url": "https://signal.nfx.com/investor-lists/top-e-commerce-seed-investors"
    },
    {
      "name": "E-commerce (Pre-seed)",
      "url": "https://signal.nfx.com/investor-lists/top-e-commerce-pre-seed-investors"
    },
    {
      "name": "Marketplaces (Pre-seed)",
      "url": "https://signal.nfx.com/investor-lists/top-marketplaces-pre-seed-investors"
    },
    {
      "name": "AI (Pre-seed)",
      "url": "https://signal.nfx.com/investor-lists/top-ai-pre-seed-investors"
    },
    {
      "name": "Marketplaces (Seed)",
      "url": "https://signal.nfx.com/investor-lists/top-marketplaces-seed-investors"
    }
  ],
  "investments": [],
  "experience": [
    {
      "position": "Founder, CEO",
      "company": "GroupPulse, Inc.",
      "dates": "2009 - 2011"
    },
    {
      "position": "Director of Emerging Platforms",
      "company": "Google",
      "dates": "2008 - 2009"
    },
    {
      "position": "Director of Commerce and Analytics",
      "company": "Google",
      "dates": "2005 - 2008"
    },
    {
      "position": "Head of Syndication Verticals",
      "company": "Google",
      "dates": "2003 - 2005"
    },
    {
      "position": "Entrepreneur in Residence - Consultant",
      "company": "Benchmark Capital",
      "dates": "2002 - 2002"
    },
    {
      "position": "Founder, COO and VP Product",
      "company": "Flutter.com - Betfair.com",
      "dates": "1999 - 2002"
    },
    {
      "position": "Consultant and Case Team Leader",
      "company": "Bain & Company",
      "dates": "1997 - 1999"
    },
    {
      "position": "Sr. Consultant",
      "company": "Accenture",
      "dates": "1991 - 1995"
    }
  ],
  "socials": {
    "linkedin": "https://www.linkedin.com/pub/vince-monical/4/667/632/",
    "angellist": "https://www.angel.co/vince-monical",
    "crunchbase": "https://www.crunchbase.com/person/vince-monical"
  },
  "profilePicture": null,
  "profileUrl": "https://signal.nfx.com/investors/vince-monical",
  "slug": "vince-monical",
  "scraped_at": "2026-02-24T13:31:07.083685"
}